loguru_discord_sink-0.1.2.dist-info/METADATA
loguru_discord_sink-0.1.2.dist-info/WHEEL
loguru_discord_sink-0.1.2.dist-info/entry_points.txt
loguru_discord_sink-0.1.2.dist-info/licenses/LICENSE.md
loguru_discord_sink/__init__.py
loguru_discord_sink/constants.py
loguru_discord_sink/handler.py
loguru_discord_sink/types.py
loguru_discord_sink-0.1.2.dist-info/RECORD
