Metadata-Version: 2.1
Name: loguru-discord-sink
Version: 0.1.2
Summary: A Loguru sink that outputs logs to a Discord webhook.
Keywords: loguru,logging,discord,webhook
Author-Email: =?utf-8?q?Elvira_Ram=C3=ADrez?= <elvirarp92@gmail.com>
License: MIT
Requires-Python: >=3.10
Requires-Dist: loguru>=0.7.3
Requires-Dist: requests>=2.32.5
Requires-Dist: setuptools>=80.9.0
